Metadata-Version: 2.1
Name: jax-cosmo
Version: 0.1rc9
Summary: Differentiable Python Cosmology Library
Home-page: https://github.com/DifferentiableUniverseInitiative/jax_cosmo
Author: jax-cosmo developers
License: UNKNOWN
Platform: UNKNOWN
Classifier: Programming Language :: Python :: 3.6
Classifier: Programming Language :: Python :: 3.7
Classifier: Programming Language :: Python :: 3.8
Classifier: License :: OSI Approved :: MIT License
Classifier: Operating System :: MacOS
Classifier: Operating System :: POSIX :: Linux
Classifier: Topic :: Scientific/Engineering
Classifier: Intended Audience :: Science/Research
Classifier: Intended Audience :: Developers
License-File: LICENSE
